[
  {
    "full_name": "bobbyiliev/introduction-to-docker-ebook",
    "stargazers_count": 570,
    "open_issues_count": 3,
    "forks_count": 123
  },
  {
    "full_name": "moinulmoin/chadnext",
    "stargazers_count": 1314,
    "open_issues_count": 15,
    "forks_count": 139
  },
  {
    "full_name": "Caknoooo/go-gin-clean-starter",
    "stargazers_count": 190,
    "open_issues_count": 0,
    "forks_count": 18
  },
  {
    "full_name": "bxcodec/go-clean-arch",
    "stargazers_count": 10000,
    "open_issues_count": 36,
    "forks_count": 1304
  },
  {
    "full_name": "qiangxue/go-rest-api",
    "stargazers_count": 1675,
    "open_issues_count": 12,
    "forks_count": 279
  },
  {
    "full_name": "ospfranco/sol",
    "stargazers_count": 2703,
    "open_issues_count": 6,
    "forks_count": 145
  },
  {
    "full_name": "wuyichen24/system-design-interview",
    "stargazers_count": 119,
    "open_issues_count": 5,
    "forks_count": 47
  },
  {
    "full_name": "shadcn-ui/taxonomy",
    "stargazers_count": 19149,
    "open_issues_count": 218,
    "forks_count": 2701
  },
  {
    "full_name": "ddsuhaimi/fullstack-boilerplate",
    "stargazers_count": 3,
    "open_issues_count": 0,
    "forks_count": 3
  },
  {
    "full_name": "chhpt/nextjs-starter",
    "stargazers_count": 142,
    "open_issues_count": 11,
    "forks_count": 32
  },
  {
    "full_name": "jpedroschmitz/typescript-nextjs-starter",
    "stargazers_count": 1441,
    "open_issues_count": 2,
    "forks_count": 162
  },
  {
    "full_name": "bbc/REST-API-example",
    "stargazers_count": 210,
    "open_issues_count": 2,
    "forks_count": 1275
  },
  {
    "full_name": "rmanguinho/clean-react",
    "stargazers_count": 1478,
    "open_issues_count": 11,
    "forks_count": 306
  },
  {
    "full_name": "KaiHotz/react-rollup-boilerplate",
    "stargazers_count": 312,
    "open_issues_count": 2,
    "forks_count": 68
  },
  {
    "full_name": "ariaghora/libdtree",
    "stargazers_count": 9,
    "open_issues_count": 1,
    "forks_count": 0
  },
  {
    "full_name": "CaiJimmy/hugo-theme-stack",
    "stargazers_count": 6248,
    "open_issues_count": 19,
    "forks_count": 1954
  },
  {
    "full_name": "adityatelange/hugo-PaperMod",
    "stargazers_count": 13063,
    "open_issues_count": 80,
    "forks_count": 3326
  },
  {
    "full_name": "ariaghora/villard",
    "stargazers_count": 10,
    "open_issues_count": 0,
    "forks_count": 1
  },
  {
    "full_name": "yehezkielgunawan/yehezgun-v3",
    "stargazers_count": 56,
    "open_issues_count": 8,
    "forks_count": 2
  },
  {
    "full_name": "carbon-language/carbon-lang",
    "stargazers_count": 33626,
    "open_issues_count": 205,
    "forks_count": 1519
  },
  {
    "full_name": "prettier/pretty-quick",
    "stargazers_count": 2287,
    "open_issues_count": 16,
    "forks_count": 86
  },
  {
    "full_name": "rully-saputra15/todolist",
    "stargazers_count": 5,
    "open_issues_count": 0,
    "forks_count": 0
  },
  {
    "full_name": "kvokov/oh-my-fullstack",
    "stargazers_count": 174,
    "open_issues_count": 16,
    "forks_count": 24
  },
  {
    "full_name": "hugotox/nextjs-cookie-demo",
    "stargazers_count": 32,
    "open_issues_count": 11,
    "forks_count": 5
  },
  {
    "full_name": "async-labs/saas",
    "stargazers_count": 4434,
    "open_issues_count": 19,
    "forks_count": 742
  },
  {
    "full_name": "ixartz/Next-js-Boilerplate",
    "stargazers_count": 12609,
    "open_issues_count": 6,
    "forks_count": 2361
  },
  {
    "full_name": "jeeehaan/QoDe",
    "stargazers_count": 1,
    "open_issues_count": 0,
    "forks_count": 1
  },
  {
    "full_name": "theodorusclarence/ts-nextjs-tailwind-starter",
    "stargazers_count": 3406,
    "open_issues_count": 12,
    "forks_count": 612
  },
  {
    "full_name": "makinhs/toptal-rest-series",
    "stargazers_count": 314,
    "open_issues_count": 6,
    "forks_count": 135
  },
  {
    "full_name": "djizco/mern-boilerplate",
    "stargazers_count": 288,
    "open_issues_count": 5,
    "forks_count": 100
  }
]